DESCRIPTION.rst
MANIFEST.in
README.rst
setup.cfg
setup.py
vilas/GromacsMD.py
vilas/LabpiAnalyzer.py
vilas/LabpiAnalyzer.py~
vilas/LabpiConfiguration.kv
vilas/LabpiConfiguration.py
vilas/LabpiLoad.kv
vilas/LabpiLoad.py
vilas/LabpiReceptor.kv
vilas/LabpiReceptor.py
vilas/LabpiRun.py
vilas/LabpiRunning.kv
vilas/LabpiRunning.py
vilas/LabpiSetting.kv
vilas/LabpiSetting.py
vilas/Utils.py
vilas/__init__.py
vilas/main.py
vilas/parsePdb.py
vilas/test.py
vilas/vilas.kv
vilas.egg-info/PKG-INFO
vilas.egg-info/SOURCES.txt
vilas.egg-info/dependency_links.txt
vilas.egg-info/entry_points.txt
vilas.egg-info/requires.txt
vilas.egg-info/top_level.txt
vilas/config/apolar_sasa.mdp
vilas/config/apolar_sav.mdp
vilas/config/ions.mdp
vilas/config/md.mdp
vilas/config/md_md.mdp
vilas/config/md_pull.mdp
vilas/config/md_pull_5.mdp
vilas/config/md_pull_5x.mdp
vilas/config/minim.mdp
vilas/config/npt.mdp
vilas/config/nvt.mdp
vilas/config/pbsa.mdp
vilas/config/plumed.dat
vilas/config/polar.mdp
vilas/img/1.png
vilas/img/1_dis.png
vilas/img/2.png
vilas/img/2_dis.png
vilas/img/3.png
vilas/img/3_dis.png
vilas/img/4.png
vilas/img/4_dis.png
vilas/img/__init__.pyc
vilas/img/back.png
vilas/img/background.png
vilas/img/cross.png
vilas/img/eye.png
vilas/img/file.png
vilas/img/info.png
vilas/img/infor.png
vilas/img/next.png
vilas/img/next_1.png
vilas/img/remove.png
vilas/img/setting.png
vilas/img/spin.png
vilas/img/tick.png
vilas/img/tick_normal.png
vilas/img/tick_select.png
vilas/source/MmPbSaStat.py
vilas/source/acpype.py
vilas/source/auto.sh
vilas/source/checkMdrun.py
vilas/source/distribute.py
vilas/source/distribute_pull.sh
vilas/source/gromacs.sh
vilas/source/gromacs.sh~
vilas/source/icst
vilas/source/loop_pull.sh
vilas/source/mathplot.py
vilas/source/nowater.py
vilas/source/optimize_ligand.sh
vilas/source/optimize_ligands.sh
vilas/source/parse_mmpbsa.py
vilas/source/parse_pull.py
vilas/source/parse_pull.sh
vilas/source/pullana.py
vilas/source/rotate.py
vilas/source/rotate.py~
vilas/source/setbox.py
vilas/source/setbox.py~
vilas/source/smd50.sh
vilas/source/steermd.sh
vilas/source/top_pull.py