Metadata-Version: 1.1
Name: vilas
Version: 0.1.4
Summary: Auto tools for Steered Molecule Simulation in Gromacs
Home-page: https://github.com/comobiophys/vilas
Author: quytruong
Author-email: support@comobiophys.com
License: MIT
Keywords: gromacs,tools,steered,vilas
Platform: UNKNOWN
Classifier: Development Status :: 3 - Alpha
Classifier: Intended Audience :: Developers
Classifier: Topic :: Software Development :: Build Tools
Classifier: License :: OSI Approved :: MIT License
Classifier: Programming Language :: Python :: 2.7
Classifier: Programming Language :: Python :: 3
Classifier: Programming Language :: Python :: 3.2
Classifier: Programming Language :: Python :: 3.3
Classifier: Programming Language :: Python :: 3.4
